{
  "tenantScoped": [
    "ActivityEvent",
    "AuditLog",
    "AutomationExecution",
    "AutomationRule",
    "Cita",
    "ClientUser",
    "Cliente",
    "Comunicacion",
    "Disponibilidad",
    "Document",
    "DocumentFolder",
    "DocumentTrash",
    "Documento",
    "Encuesta",
    "EventoAcademico",
    "EventoBitacora",
    "Incidencia",
    "IntegrationConnector",
    "IntegrationExecution",
    "ItemInventario",
    "MessageDelivery",
    "MessageTemplate",
    "NotificationAudit",
    "NotificationBatch",
    "NotificationDefinition",
    "NotificationDigest",
    "NotificationInstance",
    "NotificationPreference",
    "NotificationReceipt",
    "PagoIntent",
    "PlantillaDocumento",
    "Presupuesto",
    "Resource",
    "SearchEntry",
    "Sistema",
    "Tarea",
    "TenantSecret",
    "User",
    "Webhook",
    "WorkflowActiveBranch",
    "WorkflowAudit",
    "WorkflowDefinition",
    "WorkflowExecution",
    "WorkflowInstance",
    "WorkflowTimer",
    "WorkflowUserTask",
    "WorkflowVariable"
  ],
  "clienteScoped": [
    "ActivityEvent",
    "Cita",
    "ClientUser",
    "Comunicacion",
    "Documento",
    "Incidencia",
    "PagoIntent",
    "Presupuesto",
    "SearchEntry",
    "Sistema",
    "Tarea"
  ],
  "allModels": [
    "ActivityEvent",
    "AuditLog",
    "AutomationExecution",
    "AutomationExecutionStep",
    "AutomationRule",
    "Cita",
    "ClientUser",
    "Cliente",
    "Comunicacion",
    "Disponibilidad",
    "Document",
    "DocumentFolder",
    "DocumentTrash",
    "DocumentVersion",
    "Documento",
    "Encuesta",
    "EventoAcademico",
    "EventoBitacora",
    "Incidencia",
    "IntegrationConnector",
    "IntegrationExecution",
    "ItemInventario",
    "MessageDelivery",
    "MessageTemplate",
    "NotificationAudit",
    "NotificationBatch",
    "NotificationDefinition",
    "NotificationDigest",
    "NotificationInstance",
    "NotificationPreference",
    "NotificationReceipt",
    "PagoIntent",
    "PlantillaDocumento",
    "Presupuesto",
    "Resource",
    "SearchEntry",
    "ShareLink",
    "Sistema",
    "Tarea",
    "Tenant",
    "TenantSecret",
    "User",
    "Webhook",
    "WorkflowActiveBranch",
    "WorkflowAudit",
    "WorkflowDefinition",
    "WorkflowDefinitionVersion",
    "WorkflowExecution",
    "WorkflowInstance",
    "WorkflowTimer",
    "WorkflowUserTask",
    "WorkflowVariable",
    "account",
    "invitation",
    "member",
    "organization",
    "session",
    "user",
    "verification"
  ],
  "byField": {
    "tenantId": [
      "User",
      "Cliente",
      "ClientUser",
      "Presupuesto",
      "Webhook",
      "Sistema",
      "ItemInventario",
      "EventoBitacora",
      "Tarea",
      "Documento",
      "Disponibilidad",
      "Resource",
      "Incidencia",
      "Cita",
      "AuditLog",
      "Comunicacion",
      "PlantillaDocumento",
      "PagoIntent",
      "ActivityEvent",
      "Encuesta",
      "EventoAcademico",
      "SearchEntry",
      "TenantSecret",
      "AutomationRule",
      "AutomationExecution",
      "MessageTemplate",
      "MessageDelivery",
      "DocumentFolder",
      "Document",
      "DocumentTrash",
      "WorkflowDefinition",
      "WorkflowInstance",
      "WorkflowExecution",
      "WorkflowUserTask",
      "WorkflowTimer",
      "WorkflowAudit",
      "WorkflowVariable",
      "WorkflowActiveBranch",
      "NotificationDefinition",
      "NotificationInstance",
      "NotificationPreference",
      "NotificationBatch",
      "NotificationReceipt",
      "NotificationAudit",
      "NotificationDigest",
      "IntegrationConnector",
      "IntegrationExecution"
    ],
    "clienteId": [
      "ClientUser",
      "Presupuesto",
      "Sistema",
      "Tarea",
      "Documento",
      "Incidencia",
      "Cita",
      "Comunicacion",
      "PagoIntent",
      "ActivityEvent",
      "SearchEntry"
    ]
  },
  "timestamp": "2026-07-20T17:21:47.451Z"
}
